README.md
setup.py
dopltech/protos/__init__.py
dopltech/protos/catheter_path_service_pb2.py
dopltech/protos/catheter_path_service_pb2_grpc.py
dopltech/protos/common_pb2.py
dopltech/protos/common_pb2_grpc.py
dopltech/protos/device_service_pb2.py
dopltech/protos/device_service_pb2_grpc.py
dopltech/protos/session_service_pb2.py
dopltech/protos/session_service_pb2_grpc.py
dopltech/protos/state_manager_pb2.py
dopltech/protos/state_manager_pb2_grpc.py
dopltech_api_protos.egg-info/PKG-INFO
dopltech_api_protos.egg-info/SOURCES.txt
dopltech_api_protos.egg-info/dependency_links.txt
dopltech_api_protos.egg-info/requires.txt
dopltech_api_protos.egg-info/top_level.txt