Metadata-Version: 1.0
Name: dopltech-api-protos
Version: 0.0.1
Summary: Dopl Technologies API protos
Home-page: UNKNOWN
Author: Ryan James
Author-email: ryan@dopltechnologies.com
License: UNKNOWN
Platform: UNKNOWN
